{
    "colleges": [
        [
            "Bidhan Chandra Krishi Viswa Vidyalaya",
            [
                {
                    "branch": "Agricultural Engineering",
                    "gen_or": "1112",
                    "gen_cr": "5110",
                    "obc_or": "11042",
                    "obc_cr": "13564"
                }
            ],
            "https://www.bckv.edu.in/site_admin/home_banner/993437.jpg",
            "https://www.google.com/maps/place/Bidhan+Chandra+Krishi+Viswavidyalaya/@22.9452453,88.5335715,15z/data=!4m5!3m4!1s0x0:0xa13e16b49259cb3a!8m2!3d22.9452453!4d88.5335715"
        ],
        [
            "Department Of Jute And Fibre Technology, Calcutta University",
            [
                {
                    "branch": "Jute & Fibre Technology",
                    "gen_or": "5475",
                    "gen_cr": "17807",
                    "obc_or": "19448",
                    "obc_cr": "28277"
                }
            ],
            "http://4.bp.blogspot.com/-fu-2anj7V6k/Tu7pgPcG2pI/AAAAAAAAAkI/dSZHKLpGakE/s320/IJT.png",
            "https://www.google.com/maps/place/Department+of+Jute+and+Fibre+Technology,+Institute+of+Jute+Technology,+University+of+Calcutta+./@22.5278234,88.36442,15z/data=!4m5!3m4!1s0x0:0x2b161ec004f48f05!8m2!3d22.5278234!4d88.36442"
        ],
        [
            "Jadavpur University",
            [
                {
                    "branch": "Architecture",
                    "gen_or": "1170",
                    "gen_cr": "5217",
                    "obc_or": "11918",
                    "obc_cr": "22764"
                },
                {
                    "branch": "B.Pharm/Pharmaceutical Technology",
                    "gen_or": "792",
                    "gen_cr": "4222",
                    "obc_or": "4490",
                    "obc_cr": "6536"
                },
                {
                    "branch": "Chemical Engineering",
                    "gen_or": "368",
                    "gen_cr": "915",
                    "obc_or": "3585",
                    "obc_cr": "6105"
                },
                {
                    "branch": "Civil Engineering",
                    "gen_or": "608",
                    "gen_cr": "1009",
                    "obc_or": "1730",
                    "obc_cr": "6411"
                },
                {
                    "branch": "Computer Science & Engineering/Computer Science & Technology",
                    "gen_or": "6",
                    "gen_cr": "153",
                    "obc_or": "154",
                    "obc_cr": "784"
                },
                {
                    "branch": "Construction Engineering",
                    "gen_or": "971",
                    "gen_cr": "1553",
                    "obc_or": "8475",
                    "obc_cr": "9145"
                },
                {
                    "branch": "Electrical Engineering",
                    "gen_or": "96",
                    "gen_cr": "508",    
                    "obc_or": "1160",
                    "obc_cr": "3354"
                },
                {
                    "branch": "Electronics & Communication Engineering",
                    "gen_or": "7",
                    "gen_cr": "255",    
                    "obc_or": "507",
                    "obc_cr": "1450"
                },
                {
                    "branch": "Food Technology And Bio Chemical Engineering",
                    "gen_or": "1144",
                    "gen_cr": "2168",    
                    "obc_or": "6115",
                    "obc_cr": "7850"
                },
                {
                    "branch": "Information Technology",
                    "gen_or": "179",
                    "gen_cr": "536",    
                    "obc_or": "1642",
                    "obc_cr": "3519"
                },
                {
                    "branch": "Instrumentation Engineering",
                    "gen_or": "555",
                    "gen_cr": "745",    
                    "obc_or": "3570",
                    "obc_cr": "4977"
                },
                {
                    "branch": "Mechanical Engineering",
                    "gen_or": "73",
                    "gen_cr": "627",    
                    "obc_or": "1364",
                    "obc_cr": "4406"
                },
                {
                    "branch": "Metallurgical Engineering",
                    "gen_or": "717",
                    "gen_cr": "1130",    
                    "obc_or": "5532",
                    "obc_cr": "7088"
                },
                {
                    "branch": "Power Engineering/Power Plant Engineering",
                    "gen_or": "841",
                    "gen_cr": "1531",    
                    "obc_or": "7087",
                    "obc_cr": "7941"
                },
                {
                    "branch": "Printing Engineering/Printing Technology",
                    "gen_or": "1555",
                    "gen_cr": "2328",    
                    "obc_or": "11399",
                    "obc_cr": "14307"
                },
                {
                    "branch": "Production Engineering",
                    "gen_or": "640",
                    "gen_cr": "1133",    
                    "obc_or": "5330",
                    "obc_cr": "7178"
                }
            ],
            "https://collegetimes.co/wp-content/uploads/jadavpur-university-jadavpur-1.jpg",
            "https://www.google.co.in/search?source=hp&ei=UK8aW-OqH8u7rQHJ0J6oBQ&q=jadavpur%20university%20location&oq=jadavpur+university+locatipn&gs_l=psy-ab.3..0i13k1l2j0i22i30k1l4j0i8i13i30k1.1793.8558.0.8873.25.18.4.0.0.0.376.3259.2-5j6.12.0....0...1.1.64.psy-ab..11.14.3235.6..0j38j35i39k1j0i67k1j0i131k1j33i160k1.160.tM2rxgNXELU&npsic=0&rflfq=1&rlha=0&rllag=22528539,88391681,4192&tbm=lcl&rldimm=5088454007991913490&ved=0ahUKEwjOrpzxvsTbAhVFqY8KHa0xArAQvS4ITDAC&rldoc=1&tbs=lrf:!2m1!1e2!3sIAE,lf:1,lf_ui:2#rlfi=hd:;si:;mv:!1m3!1d35317.896774808454!2d88.3844615!3d22.528713349999997!2m3!1f0!2f0!3f0!3m2!1i190!2i230!4f13.1"
        ],
        [
            "Maulana Abul Kalam Azad University Of Technology, West Bengal",
            [
                {
                    "branch": "Computer Science & Engineering",
                    "gen_or": "959",
                    "gen_cr": "2232",
                    "obc_or": "4305",
                    "obc_cr": "6858"
                },
                {
                    "branch": "Information Technology",
                    "gen_or": "1583",
                    "gen_cr": "3421",
                    "obc_or": "9060",
                    "obc_cr": "11449"
                }
            ],
            "https://eisamay.indiatimes.com/photo/63809707/pic.jpg",
            "https://www.google.co.in/maps/place/Maulana+Abul+Kalam+Azad+University+of+Technology,+West+Bengal/@22.596544,88.417305,15z/data=!4m2!3m1!1s0x0:0x5db3ee28f1b792d5?sa=X&ved=0ahUKEwjzu8HXv8TbAhWQfn0KHfduAdMQ_BII3AEwCg"
        ],
        [
            "University Institute Of Technology, Burdwan",
            [
                {
                    "branch": "Applied Electronics & Instrumentation Engineering",
                    "gen_or": "4347",
                    "gen_cr": "17167",
                    "obc_or": "0",
                    "obc_cr": "0"
                },
                {
                    "branch": "Civil Engineering",
                    "gen_or": "2862",
                    "gen_cr": "10244",
                    "obc_or": "0",
                    "obc_cr": "0"
                },
                {
                    "branch": "Computer Science & Engineering",
                    "gen_or": "1303",
                    "gen_cr": "6248",
                    "obc_or": "0",
                    "obc_cr": "0"
                },
                {
                    "branch": "Electrical Engineering",
                    "gen_or": "2714",
                    "gen_cr": "9740",
                    "obc_or": "0",
                    "obc_cr": "0"
                },
                {
                    "branch": "Electronics & Communication Engineering",
                    "gen_or": "3958",
                    "gen_cr": "10636",
                    "obc_or": "0",
                    "obc_cr": "0"
                },
                {
                    "branch": "Information Technology",
                    "gen_or": "6062",
                    "gen_cr": "12860",
                    "obc_or": "0",
                    "obc_cr": "0"
                }
            ],
            "http://www.buruniv.ac.in/uit/uit_files/uit1.JPG",
            "https://www.google.co.in/maps/place/University+Institute+of+Technology/@23.2572818,87.8468376,15z/data=!4m2!3m1!1s0x0:0x37a42f6b23df16cd?sa=X&ved=0ahUKEwjVlpbkv8TbAhXLXSsKHUmoB1UQ_BII3QEwCg"
        ],
        [
            "University Of Calcutta",
            [
                {
                    "branch": "Chemical Engineering",
                    "gen_or": "1423",
                    "gen_cr": "2499",
                    "obc_or": "7419",
                    "obc_cr": "7419"
                },
                {
                    "branch": "Chemical Technology",
                    "gen_or": "2584",
                    "gen_cr": "4796",
                    "obc_or": "8838",
                    "obc_cr": "8838"
                },
                {
                    "branch": "Computer Science & Engineering",
                    "gen_or": "653",
                    "gen_cr": "1273",
                    "obc_or": "5107",
                    "obc_cr": "5107"
                },
                {
                    "branch": "Electrical Engineering",
                    "gen_or": "892",
                    "gen_cr": "1661",
                    "obc_or": "4005",
                    "obc_cr": "4005"
                },
                {
                    "branch": "Information Technology",
                    "gen_or": "1305",
                    "gen_cr": "1856",
                    "obc_or": "8297",
                    "obc_cr": "8297"
                },
                {
                    "branch": "Instrumentation Engineering",
                    "gen_or": "1821",
                    "gen_cr": "2550",
                    "obc_or": "12449",
                    "obc_cr": "12449"
                },
                {
                    "branch": "Optics & Optoelectronics",
                    "gen_or": "2597",
                    "gen_cr": "3794",
                    "obc_or": "8173",
                    "obc_cr": "8173"
                },
                {
                    "branch": "Polymer Science & Technology",
                    "gen_or": "2187",
                    "gen_cr": "5034",
                    "obc_or": "13358",
                    "obc_cr": "13358"
                }
            ],
            "https://www.iaspaper.net/wp-content/uploads/2017/11/University-of-Calcutta-Results.jpg",
            "https://www.google.co.in/maps/place/University+of+Calcutta/@22.5752469,88.3627129,15z/data=!4m2!3m1!1s0x0:0x55c32ac6ac01553d?sa=X&ved=0ahUKEwjd-_mjzsfbAhWKCMAKHc0_A_MQ_BIIrwEwCg"
        ],
        [
            "University Of Kalyani, Science Instrumentation Centre",
            [
                {
                    "branch": "Applied Electronics & Instrumentation Engineering",
                    "gen_or": "1234",
                    "gen_cr": "5161",
                    "obc_or": "13079",
                    "obc_cr": "18209"
                },
                {
                    "branch": "Information Technology",
                    "gen_or": "1058",
                    "gen_cr": "3678",
                    "obc_or": "12122",
                    "obc_cr": "12419"
                }
            ],
            "https://static-collegedunia.com/public/college_data/images/appImage/26020_Kalyani_New.jpg",
            "https://www.google.co.in/maps/place/University+of+Calcutta/@22.5752469,88.3627129,15z/data=!4m2!3m1!1s0x0:0x55c32ac6ac01553d?sa=X&ved=0ahUKEwjd-_mjzsfbAhWKCMAKHc0_A_MQ_BIIrwEwCg"
        ],
        [
            "Uttar Banga Krishi Viswa Vidyalaya",
            [
                {
                    "branch": "Agricultural Engineering",
                    "gen_or": "5187",
                    "gen_cr": "7687",
                    "obc_or": "8164",
                    "obc_cr": "9232"
                }
            ],
            "https://getmyuni.azureedge.net/college-image/big/uttar-banga-krishi-vishwavidyalaya-cooch-behar.jpg",
            "https://www.google.co.in/maps/place/University+of+Calcutta/@22.5752469,88.3627129,15z/data=!4m2!3m1!1s0x0:0x55c32ac6ac01553d?sa=X&ved=0ahUKEwjd-_mjzsfbAhWKCMAKHc0_A_MQ_BIIrwEwCg"
        ],
        [
            "West Bengal University Of Animal & Fishery Sciences",
            [
                {
                    "branch": "Dairy Technology",
                    "gen_or": "5216",
                    "gen_cr": "12952",
                    "obc_or": "14781",
                    "obc_cr": "21140"
                }
            ],
            "http://photos.wikimapia.org/p/00/03/82/63/94_big.jpg",
            "https://www.google.co.in/maps/place/University+of+Calcutta/@22.5752469,88.3627129,15z/data=!4m2!3m1!1s0x0:0x55c32ac6ac01553d?sa=X&ved=0ahUKEwjd-_mjzsfbAhWKCMAKHc0_A_MQ_BIIrwEwCg"
        ],
        [
            "Cooch Behar Government Engineering College, Cooch Behar",
            [
                {
                    "branch": "Civil Engineering",
                    "gen_or": "2765",
                    "gen_cr": "14382",
                    "obc_or": "16572",
                    "obc_cr": "23216"
                },
                {
                    "branch": "Computer Science & Engineering",
                    "gen_or": "4758",
                    "gen_cr": "11028",
                    "obc_or": "11596",
                    "obc_cr": "15779"
                },
                {
                    "branch": "Electrical Engineering",
                    "gen_or": "6733",
                    "gen_cr": "13143",
                    "obc_or": "13500",
                    "obc_cr": "24945"
                },
                {
                    "branch": "Electronics & Communication Engineering",
                    "gen_or": "6197",
                    "gen_cr": "14387",
                    "obc_or": "23029",
                    "obc_cr": "25831"
                },
                {
                    "branch": "Mechanical Engineering",
                    "gen_or": "4137",
                    "gen_cr": "14403",
                    "obc_or": "14684",
                    "obc_cr": "24219"
                }
            ],
            "https://images.static-collegedunia.com/public/college_data/images/campusimage/1486183581ccamddmfs.jpg",
            "https://www.google.co.in/maps/place/University+of+Calcutta/@22.5752469,88.3627129,15z/data=!4m2!3m1!1s0x0:0x55c32ac6ac01553d?sa=X&ved=0ahUKEwjd-_mjzsfbAhWKCMAKHc0_A_MQ_BIIrwEwCg"
        ],
        [
            "Goverment College Of Engineering And Leather Technology, Kolkata",
            [
                {
                    "branch": "Computer Science & Engineering",
                    "gen_or": "2173",
                    "gen_cr": "4857",
                    "obc_or": "6284",
                    "obc_cr": "8174"
                },
                {
                    "branch": "Information Technology",
                    "gen_or": "3634",
                    "gen_cr": "8822",
                    "obc_or": "0",
                    "obc_cr": "0"
                },
                {
                    "branch": "Leather Technology",
                    "gen_or": "5726",
                    "gen_cr": "17132",
                    "obc_or": "0",
                    "obc_cr": "0"
                }
            ],
            "https://content3.jdmagicbox.com/comp/kolkata/91/033p9993991/catalogue/government-college-of-engineering-and-leather-technology-salt-lake-city-kolkata-engineering-colleges-3hdoctx.jpg",
            "https://www.google.co.in/maps/place/University+of+Calcutta/@22.5752469,88.3627129,15z/data=!4m2!3m1!1s0x0:0x55c32ac6ac01553d?sa=X&ved=0ahUKEwjd-_mjzsfbAhWKCMAKHc0_A_MQ_BIIrwEwCg"
        ],
        [
            "Govt. College Of Engg. & Textile Technology, Berhampore",
            [
                {
                    "branch": "Computer Science & Engineering",
                    "gen_or": "4069",
                    "gen_cr": "10299",
                    "obc_or": "0",
                    "obc_cr": "0"
                },
                {
                    "branch": "Electrical Engineering",
                    "gen_or": "4275",
                    "gen_cr": "8744",
                    "obc_or": "0",
                    "obc_cr": "0"
                },
                {
                    "branch": "Mechanical Engineering",
                    "gen_or": "4698",
                    "gen_cr": "10858",
                    "obc_or": "0",
                    "obc_cr": "0"
                },
                {
                    "branch": "Textile Technology",
                    "gen_or": "8254",
                    "gen_cr": "16398",
                    "obc_or": "17134",
                    "obc_cr": "26509"
                }
            ],
            "https://getmyuni.azureedge.net/college-images-test/government-college-of-engineering-textile-technology-murshidabad/a754655967564aa88e2ad059b966d1a7.jpeg",
            "https://www.google.co.in/maps/place/University+of+Calcutta/@22.5752469,88.3627129,15z/data=!4m2!3m1!1s0x0:0x55c32ac6ac01553d?sa=X&ved=0ahUKEwjd-_mjzsfbAhWKCMAKHc0_A_MQ_BIIrwEwCg"
        ],
        [
            "Govt. College Of Engineering & Ceramic Technology, Kolkata",
            [
                {
                    "branch": "Ceramic Enginering And Technology",
                    "gen_or": "3849",
                    "gen_cr": "10919",
                    "obc_or": "0",
                    "obc_cr": "0"
                },
                {
                    "branch": "Computer Science & Engineering",
                    "gen_or": "2443",
                    "gen_cr": "5146",
                    "obc_or": "0",
                    "obc_cr": "0"
                },
                {
                    "branch": "Information Technology",
                    "gen_or": "5374",
                    "gen_cr": "8758",
                    "obc_or": "0",
                    "obc_cr": "0"
                }
            ],
            "https://images.static-collegedunia.com/public/college_data/images/campusimage/1488629056c11.jpg",
            "https://www.google.co.in/maps/place/University+of+Calcutta/@22.5752469,88.3627129,15z/data=!4m2!3m1!1s0x0:0x55c32ac6ac01553d?sa=X&ved=0ahUKEwjd-_mjzsfbAhWKCMAKHc0_A_MQ_BIIrwEwCg"
        ],
        [
            "Govt. College Of Engineering & Textile Technology, Serampore",
            [
                {
                    "branch": "Apparel & Production & Management",
                    "gen_or": "11156",
                    "gen_cr": "19129",
                    "obc_or": "23708",
                    "obc_cr": "31067"
                },
                {
                    "branch": "Computer Science & Engineering",
                    "gen_or": "2729",
                    "gen_cr": "6386",
                    "obc_or": "6613",
                    "obc_cr": "10068"
                },
                {
                    "branch": "Information Technology",
                    "gen_or": "4812",
                    "gen_cr": "11064",
                    "obc_or": "12679",
                    "obc_cr": "15924"
                },
                {
                    "branch": "Textile Technology",
                    "gen_or": "5597",
                    "gen_cr": "14461",
                    "obc_or": "14693",
                    "obc_cr": "27165"
                }
            ],
            "https://images.static-collegedunia.com/public/college_data/images/campusimage/1488608590f1.jpg",
            "https://www.google.co.in/maps/place/University+of+Calcutta/@22.5752469,88.3627129,15z/data=!4m2!3m1!1s0x0:0x55c32ac6ac01553d?sa=X&ved=0ahUKEwjd-_mjzsfbAhWKCMAKHc0_A_MQ_BIIrwEwCg"
        ],
        [
            "Institute Of Pharmacy, Jalpaiguri",
            [
                {
                    "branch": "B.Pharm/Pharmaceutical Technology",
                    "gen_or": "612",
                    "gen_cr": "4140",
                    "obc_or": "4897",
                    "obc_cr": "6646"
                }
            ],
            "www.caluniv.ac.in/images/map_right_pic.jpg",
            "https://www.google.co.in/maps/place/University+of+Calcutta/@22.5752469,88.3627129,15z/data=!4m2!3m1!1s0x0:0x55c32ac6ac01553d?sa=X&ved=0ahUKEwjd-_mjzsfbAhWKCMAKHc0_A_MQ_BIIrwEwCg"
        ],
        [
            "Jalpaiguri Goverment Engineering College,Jalpaiguri",
            [
                {
                    "branch": "Civil Engineering",
                    "gen_or": "1829",
                    "gen_cr": "7250",
                    "obc_or": "0",
                    "obc_cr": "0"
                },
                {
                    "branch": "Computer Science & Engineering",
                    "gen_or": "1023",
                    "gen_cr": "4791",
                    "obc_or": "0",
                    "obc_cr": "0"
                },
                {
                    "branch": "Electrical Engineering",
                    "gen_or": "1484",
                    "gen_cr": "5577",
                    "obc_or": "0",
                    "obc_cr": "0"
                },
                {
                    "branch": "Electronics & Communication Engineering",
                    "gen_or": "3337",
                    "gen_cr": "5891",
                    "obc_or": "0",
                    "obc_cr": "0"
                },
                {
                    "branch": "Information Technology",
                    "gen_or": "4613",
                    "gen_cr": "8578",
                    "obc_or": "0",
                    "obc_cr": "0"
                },
                {
                    "branch": "Mechanical Engineering",
                    "gen_or": "2260",
                    "gen_cr": "5971",
                    "obc_or": "0",
                    "obc_cr": "0"
                }
            ],
            "www.caluniv.ac.in/images/map_right_pic.jpg",
            "https://www.google.co.in/maps/place/University+of+Calcutta/@22.5752469,88.3627129,15z/data=!4m2!3m1!1s0x0:0x55c32ac6ac01553d?sa=X&ved=0ahUKEwjd-_mjzsfbAhWKCMAKHc0_A_MQ_BIIrwEwCg"
        ],
        [
            "Kalyani Goverment Engineering College, Kalyani, Nadia",
            [
                {
                    "branch": "Computer Science & Engineering",
                    "gen_or": "235",
                    "gen_cr": "2077",
                    "obc_or": "0",
                    "obc_cr": "0"
                },
                {
                    "branch": "Electrical Engineering",
                    "gen_or": "625",
                    "gen_cr": "3099",
                    "obc_or": "0",
                    "obc_cr": "0"
                },
                {
                    "branch": "Electronics & Communication Engineering",
                    "gen_or": "752",
                    "gen_cr": "2846",
                    "obc_or": "0",
                    "obc_cr": "0"
                },
                {
                    "branch": "Information Technology",
                    "gen_or": "2216",
                    "gen_cr": "4470",
                    "obc_or": "0",
                    "obc_cr": "0"
                },
                {
                    "branch": "Mechanical Engineering",
                    "gen_or": "879",
                    "gen_cr": "3271",
                    "obc_or": "0",
                    "obc_cr": "0"
                }
            ],
            "www.caluniv.ac.in/images/map_right_pic.jpg",
            "https://www.google.co.in/maps/place/University+of+Calcutta/@22.5752469,88.3627129,15z/data=!4m2!3m1!1s0x0:0x55c32ac6ac01553d?sa=X&ved=0ahUKEwjd-_mjzsfbAhWKCMAKHc0_A_MQ_BIIrwEwCg"
        ],
        [
            "Purulia Government Engineering College, Purulia",
            [
                {
                    "branch": "Civil Engineering",
                    "gen_or": "6172",
                    "gen_cr": "15184",
                    "obc_or": "17370",
                    "obc_cr": "28105"
                },
                {
                    "branch": "Computer Science & Engineering",
                    "gen_or": "5779",
                    "gen_cr": "11418",
                    "obc_or": "13308",
                    "obc_cr": "16229"
                },
                {
                    "branch": "Electrical Engineering",
                    "gen_or": "5935",
                    "gen_cr": "13134",
                    "obc_or": "15613",
                    "obc_cr": "20721"
                },
                {
                    "branch": "Electronics & Communication Engineering",
                    "gen_or": "5903",
                    "gen_cr": "13683",
                    "obc_or": "18515",
                    "obc_cr": "28489"
                },
                {
                    "branch": "Mechanical Engineering",
                    "gen_or": "4854",
                    "gen_cr": "14707",
                    "obc_or": "18152",
                    "obc_cr": "24687"
                }
            ],
            "www.caluniv.ac.in/images/map_right_pic.jpg",
            "https://www.google.co.in/maps/place/University+of+Calcutta/@22.5752469,88.3627129,15z/data=!4m2!3m1!1s0x0:0x55c32ac6ac01553d?sa=X&ved=0ahUKEwjd-_mjzsfbAhWKCMAKHc0_A_MQ_BIIrwEwCg"
        ],
        [
            "Abacus Institute Of Engineering & Management, Mogra, Hooghly",
            [
                {
                    "branch": "Civil Engineering",
                    "gen_or": "23093",
                    "gen_cr": "88262",
                    "obc_or": "0",
                    "obc_cr": "0"
                },
                {
                    "branch": "Computer Science & Engineering",
                    "gen_or": "7549",
                    "gen_cr": "100160",
                    "obc_or": "0",
                    "obc_cr": "0"
                },
                {
                    "branch": "Electrical Engineering",
                    "gen_or": "11666",
                    "gen_cr": "93878",
                    "obc_or": "0",
                    "obc_cr": "0"
                },
                {
                    "branch": "Electronics & Communication Engineering",
                    "gen_or": "15668",
                    "gen_cr": "81364",
                    "obc_or": "0",
                    "obc_cr": "0"
                },
                {
                    "branch": "Mechanical Engineering",
                    "gen_or": "11791",
                    "gen_cr": "98838",
                    "obc_or": "0",
                    "obc_cr": "0"
                }
            ],
            "www.caluniv.ac.in/images/map_right_pic.jpg",
            "https://www.google.co.in/maps/place/University+of+Calcutta/@22.5752469,88.3627129,15z/data=!4m2!3m1!1s0x0:0x55c32ac6ac01553d?sa=X&ved=0ahUKEwjd-_mjzsfbAhWKCMAKHc0_A_MQ_BIIrwEwCg"
        ],
        [
            "Kalyani Goverment Engineering College, Kalyani, Nadia",
            [
                {
                    "branch": "Computer Science & Engineering",
                    "gen_or": "235",
                    "gen_cr": "2077",
                    "obc_or": "0",
                    "obc_cr": "0"
                },
                {
                    "branch": "Electrical Engineering",
                    "gen_or": "625",
                    "gen_cr": "3099",
                    "obc_or": "0",
                    "obc_cr": "0"
                },
                {
                    "branch": "Electronics & Communication Engineering",
                    "gen_or": "752",
                    "gen_cr": "2846",
                    "obc_or": "0",
                    "obc_cr": "0"
                },
                {
                    "branch": "Information Technology",
                    "gen_or": "2216",
                    "gen_cr": "4470",
                    "obc_or": "0",
                    "obc_cr": "0"
                },
                {
                    "branch": "Mechanical Engineering",
                    "gen_or": "879",
                    "gen_cr": "3271",
                    "obc_or": "0",
                    "obc_cr": "0"
                }
            ],
            "www.caluniv.ac.in/images/map_right_pic.jpg",
            "https://www.google.co.in/maps/place/University+of+Calcutta/@22.5752469,88.3627129,15z/data=!4m2!3m1!1s0x0:0x55c32ac6ac01553d?sa=X&ved=0ahUKEwjd-_mjzsfbAhWKCMAKHc0_A_MQ_BIIrwEwCg"
        ],
        [
            "Academy Of Technology, Adisaptagram, Hooghly",
            [
                {
                    "branch": "Applied Electronics & Instrumentation Engineering",
                    "gen_or": "11201",
                    "gen_cr": "93970",
                    "obc_or": "0",
                    "obc_cr": "0"
                },
                {
                    "branch": "Computer Science & Engineering",
                    "gen_or": "5794",
                    "gen_cr": "25421",
                    "obc_or": "0",
                    "obc_cr": "0"
                },
                {
                    "branch": "Electrical Engineering",
                    "gen_or": "12482",
                    "gen_cr": "53327",
                    "obc_or": "0",
                    "obc_cr": "0"
                },
                {
                    "branch": "Electronics & Communication Engineering",
                    "gen_or": "8988",
                    "gen_cr": "36578",
                    "obc_or": "0",
                    "obc_cr": "0"
                },
                {
                    "branch": "Information Technology",
                    "gen_or": "19747",
                    "gen_cr": "50255",
                    "obc_or": "0",
                    "obc_cr": "0"
                },
                {
                    "branch": "Mechanical Engineering",
                    "gen_or": "12007",
                    "gen_cr": "98279",
                    "obc_or": "0",
                    "obc_cr": "0"
                }
            ],
            "www.caluniv.ac.in/images/map_right_pic.jpg",
            "https://www.google.co.in/maps/place/University+of+Calcutta/@22.5752469,88.3627129,15z/data=!4m2!3m1!1s0x0:0x55c32ac6ac01553d?sa=X&ved=0ahUKEwjd-_mjzsfbAhWKCMAKHc0_A_MQ_BIIrwEwCg"
        ],
        [
            "Adamas University - Self Financing Private University",
            [
                {
                    "branch": "B.Pharm/Pharmaceutical Technology",
                    "gen_or": "7260",
                    "gen_cr": "55597",
                    "obc_or": "0",
                    "obc_cr": "0"
                },
                {
                    "branch": "Biotechnology",
                    "gen_or": "27685",
                    "gen_cr": "81241",
                    "obc_or": "0",
                    "obc_cr": "0"
                },
                {
                    "branch": "Civil Engineering",
                    "gen_or": "20309",
                    "gen_cr": "91585",
                    "obc_or": "0",
                    "obc_cr": "0"
                },
                {
                    "branch": "Computer Science & Engineering",
                    "gen_or": "26005",
                    "gen_cr": "89529",
                    "obc_or": "0",
                    "obc_cr": "0"
                },
                {
                    "branch": "Electrical Engineering",
                    "gen_or": "36761",
                    "gen_cr": "95862",
                    "obc_or": "0",
                    "obc_cr": "0"
                },
                {
                    "branch": "Electronics & Communication Engineering",
                    "gen_or": "46200",
                    "gen_cr": "78948",
                    "obc_or": "0",
                    "obc_cr": "0"
                },
                {
                    "branch": "Mechanical Engineering",
                    "gen_or": "34571",
                    "gen_cr": "34571",
                    "obc_or": "0",
                    "obc_cr": "0"
                }
            ],
            "www.caluniv.ac.in/images/map_right_pic.jpg",
            "https://www.google.co.in/maps/place/University+of+Calcutta/@22.5752469,88.3627129,15z/data=!4m2!3m1!1s0x0:0x55c32ac6ac01553d?sa=X&ved=0ahUKEwjd-_mjzsfbAhWKCMAKHc0_A_MQ_BIIrwEwCg"
        ],
        [
            "Aryabhatta Institute Of Engineering & Management, Panagar, Burdwan",
            [
                {
                    "branch": "Civil Engineering",
                    "gen_or": "74070",
                    "gen_cr": "93582",
                    "obc_or": "0",
                    "obc_cr": "0"
                },
                {
                    "branch": "Computer Science & Engineering",
                    "gen_or": "38075",
                    "gen_cr": "86562",
                    "obc_or": "0",
                    "obc_cr": "0"
                },
                {
                    "branch": "Electrical & Electronics Engineering",
                    "gen_or": "24710",
                    "gen_cr": "68105",
                    "obc_or": "0",
                    "obc_cr": "0"
                },
                {
                    "branch": "Electrical Engineering",
                    "gen_or": "34507",
                    "gen_cr": "96517",
                    "obc_or": "0",
                    "obc_cr": "0"
                },
                {
                    "branch": "Electronics & Communication Engineering",
                    "gen_or": "20052",
                    "gen_cr": "96419",
                    "obc_or": "0",
                    "obc_cr": "0"
                },
                {
                    "branch": "Information Technology",
                    "gen_or": "44392",
                    "gen_cr": "98298",
                    "obc_or": "0",
                    "obc_cr": "0"
                },
                {
                    "branch": "Mechanical Engineering",
                    "gen_or": "43918",
                    "gen_cr": "89068",
                    "obc_or": "0",
                    "obc_cr": "0"
                }
            ],
            "www.caluniv.ac.in/images/map_right_pic.jpg",
            "https://www.google.co.in/maps/place/University+of+Calcutta/@22.5752469,88.3627129,15z/data=!4m2!3m1!1s0x0:0x55c32ac6ac01553d?sa=X&ved=0ahUKEwjd-_mjzsfbAhWKCMAKHc0_A_MQ_BIIrwEwCg"
        ],
        [
            "Asansol Engineering College, Asansol, Burdwan",
            [
                {
                    "branch": "Applied Electronics & Instrumentation Engineering",
                    "gen_or": "13451",
                    "gen_cr": "88105",
                    "obc_or": "0",
                    "obc_cr": "0"
                },
                {
                    "branch": "Civil Engineering",
                    "gen_or": "15238",
                    "gen_cr": "89356",
                    "obc_or": "0",
                    "obc_cr": "0"
                },
                {
                    "branch": "Computer Science & Engineering",
                    "gen_or": "9055",
                    "gen_cr": "39255",
                    "obc_or": "0",
                    "obc_cr": "0"
                },
                {
                    "branch": "Electrical Engineering",
                    "gen_or": "14166",
                    "gen_cr": "91708",
                    "obc_or": "0",
                    "obc_cr": "0"
                },
                {
                    "branch": "Electronics & Communication Engineering",
                    "gen_or": "12319",
                    "gen_cr": "83923",
                    "obc_or": "0",
                    "obc_cr": "0"
                },
                {
                    "branch": "Information Technology",
                    "gen_or": "11625",
                    "gen_cr": "99887",
                    "obc_or": "0",
                    "obc_cr": "0"
                },
                {
                    "branch": "Mechanical Engineering",
                    "gen_or": "13484",
                    "gen_cr": "99580",
                    "obc_or": "0",
                    "obc_cr": "0"
                }
            ],
            "www.caluniv.ac.in/images/map_right_pic.jpg",
            "https://www.google.co.in/maps/place/University+of+Calcutta/@22.5752469,88.3627129,15z/data=!4m2!3m1!1s0x0:0x55c32ac6ac01553d?sa=X&ved=0ahUKEwjd-_mjzsfbAhWKCMAKHc0_A_MQ_BIIrwEwCg"
        ],
        [
            "B.P. Poddar Institute Of Management & Technology, Kolkata",
            [
                {
                    "branch": "Computer Science & Engineering",
                    "gen_or": "8518",
                    "gen_cr": "23196",
                    "obc_or": "0",
                    "obc_cr": "0"
                },
                {
                    "branch": "Electrical Engineering",
                    "gen_or": "5193",
                    "gen_cr": "40121",
                    "obc_or": "0",
                    "obc_cr": "0"
                },
                {
                    "branch": "Electronics & Communication Engineering",
                    "gen_or": "7316",
                    "gen_cr": "35043",
                    "obc_or": "0",
                    "obc_cr": "0"
                },
                {
                    "branch": "Information Technology",
                    "gen_or": "12675",
                    "gen_cr": "39572",
                    "obc_or": "0",
                    "obc_cr": "0"
                }
            ],
            "www.caluniv.ac.in/images/map_right_pic.jpg",
            "https://www.google.co.in/maps/place/University+of+Calcutta/@22.5752469,88.3627129,15z/data=!4m2!3m1!1s0x0:0x55c32ac6ac01553d?sa=X&ved=0ahUKEwjd-_mjzsfbAhWKCMAKHc0_A_MQ_BIIrwEwCg"
        ],
        [
            "Bankura Unnayani Institute Of Engineering, Bankura",
            [
                {
                    "branch": "Applied Electronics & Instrumentation Engineering",
                    "gen_or": "42997",
                    "gen_cr": "42997",
                    "obc_or": "0",
                    "obc_cr": "0"
                },
                {
                    "branch": "Civil Engineering",
                    "gen_or": "48016",
                    "gen_cr": "98400",
                    "obc_or": "0",
                    "obc_cr": "0"
                },
                {
                    "branch": "Computer Science & Engineering",
                    "gen_or": "23002",
                    "gen_cr": "91975",
                    "obc_or": "0",
                    "obc_cr": "0"
                },
                {
                    "branch": "Electrical Engineering",
                    "gen_or": "59225",
                    "gen_cr": "89632",
                    "obc_or": "0",
                    "obc_cr": "0"
                },
                {
                    "branch": "Electronics & Communication Engineering",
                    "gen_or": "49709",
                    "gen_cr": "92690",
                    "obc_or": "0",
                    "obc_cr": "0"
                },
                {
                    "branch": "Information Technology",
                    "gen_or": "44592",
                    "gen_cr": "54330",
                    "obc_or": "0",
                    "obc_cr": "0"
                },
                {
                    "branch": "Mechanical Engineering",
                    "gen_or": "25458",
                    "gen_cr": "77094",
                    "obc_or": "0",
                    "obc_cr": "0"
                }
            ],
            "www.caluniv.ac.in/images/map_right_pic.jpg",
            "https://www.google.co.in/maps/place/University+of+Calcutta/@22.5752469,88.3627129,15z/data=!4m2!3m1!1s0x0:0x55c32ac6ac01553d?sa=X&ved=0ahUKEwjd-_mjzsfbAhWKCMAKHc0_A_MQ_BIIrwEwCg"
        ],
        [
            "BCDA College Of Pharmacy & Technology, Hridaypur",
            [
                {
                    "branch": "B.Pharm/Pharmaceutical Technology",
                    "gen_or": "7154",
                    "gen_cr": "32743",
                    "obc_or": "0",
                    "obc_cr": "0"
                }
            ],
            "www.caluniv.ac.in/images/map_right_pic.jpg",
            "https://www.google.co.in/maps/place/University+of+Calcutta/@22.5752469,88.3627129,15z/data=!4m2!3m1!1s0x0:0x55c32ac6ac01553d?sa=X&ved=0ahUKEwjd-_mjzsfbAhWKCMAKHc0_A_MQ_BIIrwEwCg"
        ],
        [
            "Bengal College Of Engineering & Technology, Durgapur",
            [
                {
                    "branch": "Civil Engineering",
                    "gen_or": "6023",
                    "gen_cr": "98534",
                    "obc_or": "0",
                    "obc_cr": "0"
                },
                {
                    "branch": "Computer Science & Engineering",
                    "gen_or": "7890",
                    "gen_cr": "100555",
                    "obc_or": "0",
                    "obc_cr": "0"
                },
                {
                    "branch": "Electrical & Electronics Engineering",
                    "gen_or": "44077",
                    "gen_cr": "51206",
                    "obc_or": "0",
                    "obc_cr": "0"
                },
                {
                    "branch": "Electrical Engineering",
                    "gen_or": "23287",
                    "gen_cr": "97526",
                    "obc_or": "0",
                    "obc_cr": "0"
                },
                {
                    "branch": "Electronics & Communication Engineering",
                    "gen_or": "8895",
                    "gen_cr": "93243",
                    "obc_or": "0",
                    "obc_cr": "0"
                },
                {
                    "branch": "Information Technology",
                    "gen_or": "35892",
                    "gen_cr": "95917",
                    "obc_or": "0",
                    "obc_cr": "0"
                },
                {
                    "branch": "Mechanical Engineering",
                    "gen_or": "20167",
                    "gen_cr": "100881",
                    "obc_or": "0",
                    "obc_cr": "0"
                }
            ],
            "www.caluniv.ac.in/images/map_right_pic.jpg",
            "https://www.google.co.in/maps/place/University+of+Calcutta/@22.5752469,88.3627129,15z/data=!4m2!3m1!1s0x0:0x55c32ac6ac01553d?sa=X&ved=0ahUKEwjd-_mjzsfbAhWKCMAKHc0_A_MQ_BIIrwEwCg"
        ],
        [
            "Bengal College Of Engineering, Durgapur",
            [
                {
                    "branch": "Computer Science & Engineering",
                    "gen_or": "10285",
                    "gen_cr": "93225",
                    "obc_or": "0",
                    "obc_cr": "0"
                },
                {
                    "branch": "Electrical Engineering",
                    "gen_or": "31460",
                    "gen_cr": "92341",
                    "obc_or": "0",
                    "obc_cr": "0"
                },
                {
                    "branch": "Electronics & Communication Engineering",
                    "gen_or": "26156",
                    "gen_cr": "59402",
                    "obc_or": "0",
                    "obc_cr": "0"
                }
            ],
            "www.caluniv.ac.in/images/map_right_pic.jpg",
            "https://www.google.co.in/maps/place/University+of+Calcutta/@22.5752469,88.3627129,15z/data=!4m2!3m1!1s0x0:0x55c32ac6ac01553d?sa=X&ved=0ahUKEwjd-_mjzsfbAhWKCMAKHc0_A_MQ_BIIrwEwCg"
        ],
        [
            "Bengal Collge Of Pharmaceutical Science & Research, Durgapur",
            [
                {
                    "branch": "B.Pharm/Pharmaceutical Technology",
                    "gen_or": "5134",
                    "gen_cr": "54369",
                    "obc_or": "0",
                    "obc_cr": "0"
                }
            ],
            "www.caluniv.ac.in/images/map_right_pic.jpg",
            "https://www.google.co.in/maps/place/University+of+Calcutta/@22.5752469,88.3627129,15z/data=!4m2!3m1!1s0x0:0x55c32ac6ac01553d?sa=X&ved=0ahUKEwjd-_mjzsfbAhWKCMAKHc0_A_MQ_BIIrwEwCg"
        ],
        [
            "Bengal Institute Of Technology & Management, Santiniketan",
            [
                {
                    "branch": "Civil Engineering",
                    "gen_or": "65130",
                    "gen_cr": "92993",
                    "obc_or": "0",
                    "obc_cr": "0"
                },
                {
                    "branch": "Computer Science & Engineering",
                    "gen_or": "6820",
                    "gen_cr": "88191",
                    "obc_or": "0",
                    "obc_cr": "0"
                },
                {
                    "branch": "Electrical Engineering",
                    "gen_or": "74206",
                    "gen_cr": "85632",
                    "obc_or": "0",
                    "obc_cr": "0"
                },
                {
                    "branch": "Electronics & Communication Engineering",
                    "gen_or": "44301",
                    "gen_cr": "44301",
                    "obc_or": "0",
                    "obc_cr": "0"
                },
                {
                    "branch": "Mechanical Engineering",
                    "gen_or": "30612",
                    "gen_cr": "95087",
                    "obc_or": "0",
                    "obc_cr": "0"
                }
            ],
            "www.caluniv.ac.in/images/map_right_pic.jpg",
            "https://www.google.co.in/maps/place/University+of+Calcutta/@22.5752469,88.3627129,15z/data=!4m2!3m1!1s0x0:0x55c32ac6ac01553d?sa=X&ved=0ahUKEwjd-_mjzsfbAhWKCMAKHc0_A_MQ_BIIrwEwCg"
        ],
        [
            "Bengal Institute Of Technology, Dhapa, Kolkata",
            [
                {
                    "branch": "Biotechnology",
                    "gen_or": "19554",
                    "gen_cr": "76731",
                    "obc_or": "0",
                    "obc_cr": "0"
                },
                {
                    "branch": "Computer Science & Engineering",
                    "gen_or": "13519",
                    "gen_cr": "49983",
                    "obc_or": "0",
                    "obc_cr": "0"
                },
                {
                    "branch": "Electronics & Communication Engineering",
                    "gen_or": "25808",
                    "gen_cr": "97339",
                    "obc_or": "0",
                    "obc_cr": "0"
                },
                {
                    "branch": "Information Technology",
                    "gen_or": "29404",
                    "gen_cr": "88481",
                    "obc_or": "0",
                    "obc_cr": "0"
                }
            ],
            "www.caluniv.ac.in/images/map_right_pic.jpg",
            "https://www.google.co.in/maps/place/University+of+Calcutta/@22.5752469,88.3627129,15z/data=!4m2!3m1!1s0x0:0x55c32ac6ac01553d?sa=X&ved=0ahUKEwjd-_mjzsfbAhWKCMAKHc0_A_MQ_BIIrwEwCg"
        ],
        [
            "Bengal School Of Technology, Sugandha, Hooghly",
            [
                {
                    "branch": "B.Pharm/Pharmaceutical Technology",
                    "gen_or": "4704",
                    "gen_cr": "56466",
                    "obc_or": "0",
                    "obc_cr": "0"
                }
            ],
            "www.caluniv.ac.in/images/map_right_pic.jpg",
            "https://www.google.co.in/maps/place/University+of+Calcutta/@22.5752469,88.3627129,15z/data=!4m2!3m1!1s0x0:0x55c32ac6ac01553d?sa=X&ved=0ahUKEwjd-_mjzsfbAhWKCMAKHc0_A_MQ_BIIrwEwCg"
        ],
        [
            "Bharat Technology, Uluberia, Howrah",
            [
                {
                    "branch": "B.Pharm/Pharmaceutical Technology",
                    "gen_or": "13156",
                    "gen_cr": "58099",
                    "obc_or": "0",
                    "obc_cr": "0"
                }
            ],
            "www.caluniv.ac.in/images/map_right_pic.jpg",
            "https://www.google.co.in/maps/place/University+of+Calcutta/@22.5752469,88.3627129,15z/data=!4m2!3m1!1s0x0:0x55c32ac6ac01553d?sa=X&ved=0ahUKEwjd-_mjzsfbAhWKCMAKHc0_A_MQ_BIIrwEwCg"
        ],
        [
            "Birbhum Institute Of Engineering & Technology, Suri, Birbhum",
            [
                {
                    "branch": "Civil Engineering",
                    "gen_or": "42627",
                    "gen_cr": "86903",
                    "obc_or": "0",
                    "obc_cr": "0"
                },
                {
                    "branch": "Computer Science & Engineering",
                    "gen_or": "26722",
                    "gen_cr": "86497",
                    "obc_or": "0",
                    "obc_cr": "0"
                },
                {
                    "branch": "Electrical Engineering",
                    "gen_or": "44880",
                    "gen_cr": "62165",
                    "obc_or": "0",
                    "obc_cr": "0"
                },
                {
                    "branch": "Electronics & Communication Engineering",
                    "gen_or": "41150",
                    "gen_cr": "55414",
                    "obc_or": "0",
                    "obc_cr": "0"
                },
                {
                    "branch": "Mechanical Engineering",
                    "gen_or": "46552",
                    "gen_cr": "89535",
                    "obc_or": "0",
                    "obc_cr": "0"
                }
            ],
            "www.caluniv.ac.in/images/map_right_pic.jpg",
            "https://www.google.co.in/maps/place/University+of+Calcutta/@22.5752469,88.3627129,15z/data=!4m2!3m1!1s0x0:0x55c32ac6ac01553d?sa=X&ved=0ahUKEwjd-_mjzsfbAhWKCMAKHc0_A_MQ_BIIrwEwCg"
        ],
        [
            "Brainware Group Of Institutions - Savita Devi Education Trust, Barasat",
            [
                {
                    "branch": "Civil Engineering",
                    "gen_or": "45160",
                    "gen_cr": "97790",
                    "obc_or": "0",
                    "obc_cr": "0"
                },
                {
                    "branch": "Computer Science & Engineering",
                    "gen_or": "11276",
                    "gen_cr": "97215",
                    "obc_or": "0",
                    "obc_cr": "0"
                },
                {
                    "branch": "Electrical Engineering",
                    "gen_or": "31319",
                    "gen_cr": "98533",
                    "obc_or": "0",
                    "obc_cr": "0"
                },
                {
                    "branch": "Electronics & Communication Engineering",
                    "gen_or": "26004",
                    "gen_cr": "99229",
                    "obc_or": "0",
                    "obc_cr": "0"
                },
                {
                    "branch": "Mechanical Engineering",
                    "gen_or": "13004",
                    "gen_cr": "78662",
                    "obc_or": "0",
                    "obc_cr": "0"
                }
            ],
            "www.caluniv.ac.in/images/map_right_pic.jpg",
            "https://www.google.co.in/maps/place/University+of+Calcutta/@22.5752469,88.3627129,15z/data=!4m2!3m1!1s0x0:0x55c32ac6ac01553d?sa=X&ved=0ahUKEwjd-_mjzsfbAhWKCMAKHc0_A_MQ_BIIrwEwCg"
        ],
        [
            "Brainware University",
            [
                {
                    "branch": "Computer Science & Engineering",
                    "gen_or": "16836",
                    "gen_cr": "99387",
                    "obc_or": "0",
                    "obc_cr": "0"
                }
            ],
            "www.caluniv.ac.in/images/map_right_pic.jpg",
            "https://www.google.co.in/maps/place/University+of+Calcutta/@22.5752469,88.3627129,15z/data=!4m2!3m1!1s0x0:0x55c32ac6ac01553d?sa=X&ved=0ahUKEwjd-_mjzsfbAhWKCMAKHc0_A_MQ_BIIrwEwCg"
        ],
        [
            "Budge Budge Institute Of Technology, Budge-Budge",
            [
                {
                    "branch": "Civil Engineering",
                    "gen_or": "60254",
                    "gen_cr": "97730",
                    "obc_or": "0",
                    "obc_cr": "0"
                },
                {
                    "branch": "Computer Science & Engineering",
                    "gen_or": "18571",
                    "gen_cr": "95728",
                    "obc_or": "0",
                    "obc_cr": "0"
                },
                {
                    "branch": "Electrical Engineering",
                    "gen_or": "38988",
                    "gen_cr": "86097",
                    "obc_or": "0",
                    "obc_cr": "0"
                },
                {
                    "branch": "Electronics & Communication Engineering",
                    "gen_or": "20576",
                    "gen_cr": "56453",
                    "obc_or": "0",
                    "obc_cr": "0"
                },
                {
                    "branch": "Mechanical Engineering",
                    "gen_or": "54081",
                    "gen_cr": "93323",
                    "obc_or": "0",
                    "obc_cr": "0"
                }
            ],
            "www.caluniv.ac.in/images/map_right_pic.jpg",
            "https://www.google.co.in/maps/place/University+of+Calcutta/@22.5752469,88.3627129,15z/data=!4m2!3m1!1s0x0:0x55c32ac6ac01553d?sa=X&ved=0ahUKEwjd-_mjzsfbAhWKCMAKHc0_A_MQ_BIIrwEwCg"
        ],
        [
            "Calcutta Institute Of Engineering & Management, Tollygunge, Kolkata",
            [
                {
                    "branch": "Civil Engineering",
                    "gen_or": "17341",
                    "gen_cr": "88691",
                    "obc_or": "0",
                    "obc_cr": "0"
                },
                {
                    "branch": "Computer Science & Engineering",
                    "gen_or": "6828",
                    "gen_cr": "39776",
                    "obc_or": "0",
                    "obc_cr": "0"
                },
                {
                    "branch": "Electrical Engineering",
                    "gen_or": "24119",
                    "gen_cr": "100338",
                    "obc_or": "0",
                    "obc_cr": "0"
                },
                {
                    "branch": "Electronics & Communication Engineering",
                    "gen_or": "23018",
                    "gen_cr": "78691",
                    "obc_or": "0",
                    "obc_cr": "0"
                },
                {
                    "branch": "Information Technology",
                    "gen_or": "24262",
                    "gen_cr": "100343",
                    "obc_or": "0",
                    "obc_cr": "0"
                },
                {
                    "branch": "Instrumentation And Control Engineering",
                    "gen_or": "30202",
                    "gen_cr": "74125",
                    "obc_or": "0",
                    "obc_cr": "0"
                }
            ],
            "www.caluniv.ac.in/images/map_right_pic.jpg",
            "https://www.google.co.in/maps/place/University+of+Calcutta/@22.5752469,88.3627129,15z/data=!4m2!3m1!1s0x0:0x55c32ac6ac01553d?sa=X&ved=0ahUKEwjd-_mjzsfbAhWKCMAKHc0_A_MQ_BIIrwEwCg"
        ]
    ]
}